Metadata-Version: 2.1
Name: jdocdb
Version: 0.0.1
Summary: A simple and lightweight JSON mock database for small projects
Home-page: 
Author: Abhay S Prasad (KingCosma)
Author-email: abhaygorur@gmail.com
License: MIT
Keywords: datbase,json,data
Classifier: Development Status :: 5 - Production/Stable
Classifier: Intended Audience :: Education
Classifier: Operating System :: Microsoft :: Windows :: Windows 10
Classifier: License :: OSI Approved :: MIT License
Classifier: Programming Language :: Python :: 3
License-File: LICENCE.txt
